{"0": {"brute_force": {"itens": [[1, 14], [4, 833], [9, 594], [5, 862], [6, 349], [7, 115], [1, 602], [7, 69], [6, 717], [4, 668]], "total_time": "52.367646", "waste": 10, "solution": [[[4, 668], [6, 717]], [[7, 69], [1, 602], [1, 14]], [[7, 115]], [[6, 349], [4, 833]], [[5, 862]], [[9, 594]]]}, "greedy": {"itens": [[1, 14], [4, 833], [9, 594], [5, 862], [6, 349], [7, 115], [1, 602], [7, 69], [6, 717], [4, 668]], "total_time": "0.000036", "waste": 10, "solution": [[[1, 14], [7, 69], [1, 602]], [[7, 115]], [[6, 349], [4, 668]], [[9, 594]], [[6, 717], [4, 833]], [[5, 862]]]}}, "1": {"brute_force": {"itens": [[9, 180], [8, 25], [1, 158], [4, 944], [4, 195], [8, 75], [2, 352], [2, 740], [8, 656], [7, 910]], "total_time": "52.530760", "waste": 7, "solution": [[[7, 910], [2, 740], [1, 158]], [[8, 656], [2, 352]], [[8, 75]], [[4, 195], [4, 944]], [[8, 25]], [[9, 180]]]}, "greedy": {"itens": [[9, 180], [8, 25], [1, 158], [4, 944], [4, 195], [8, 75], [2, 352], [2, 740], [8, 656], [7, 910]], "total_time": "0.000029", "waste": 7, "solution": [[[8, 25], [1, 158]], [[8, 75], [2, 352]], [[9, 180]], [[4, 195], [2, 740], [4, 944]], [[8, 656]], [[7, 910]]]}}, "2": {"brute_force": {"itens": [[2, 271], [4, 650], [6, 190], [5, 512], [6, 430], [8, 440], [1, 331], [5, 953], [6, 459], [8, 435]], "total_time": "43.478730", "waste": 9, "solution": [[[8, 435], [1, 331]], [[6, 459], [4, 650]], [[5, 953], [5, 512]], [[8, 440], [2, 271]], [[6, 430]], [[6, 190]]]}, "greedy": {"itens": [[2, 271], [4, 650], [6, 190], [5, 512], [6, 430], [8, 440], [1, 331], [5, 953], [6, 459], [8, 435]], "total_time": "0.000046", "waste": 9, "solution": [[[6, 190], [2, 271], [1, 331]], [[6, 430], [4, 650]], [[8, 435]], [[8, 440]], [[6, 459]], [[5, 512], [5, 953]]]}}, "3": {"brute_force": {"itens": [[3, 912], [8, 531], [6, 575], [3, 648], [9, 123], [5, 169], [7, 278], [3, 970], [3, 199], [3, 911]], "total_time": "45.743396", "waste": 10, "solution": [[[3, 911], [3, 199], [3, 970]], [[7, 278], [3, 648]], [[5, 169], [3, 912]], [[9, 123]], [[6, 575]], [[8, 531]]]}, "greedy": {"itens": [[3, 912], [8, 531], [6, 575], [3, 648], [9, 123], [5, 169], [7, 278], [3, 970], [3, 199], [3, 911]], "total_time": "0.000028", "waste": 10, "solution": [[[9, 123]], [[5, 169], [3, 199]], [[7, 278], [3, 648]], [[8, 531]], [[6, 575], [3, 911]], [[3, 912], [3, 970]]]}}, "4": {"brute_force": {"itens": [[9, 807], [2, 875], [3, 161], [8, 999], [3, 67], [1, 793], [9, 374], [9, 441], [8, 977], [1, 160]], "total_time": "40.749221", "waste": 7, "solution": [[[1, 160], [8, 977], [1, 793]], [[9, 441]], [[9, 374]], [[3, 67], [3, 161], [2, 875]], [[8, 999]], [[9, 807]]]}, "greedy": {"itens": [[9, 807], [2, 875], [3, 161], [8, 999], [3, 67], [1, 793], [9, 374], [9, 441], [8, 977], [1, 160]], "total_time": "0.000028", "waste": 7, "solution": [[[3, 67], [1, 160], [3, 161], [1, 793], [2, 875]], [[9, 374]], [[9, 441]], [[9, 807]], [[8, 977]], [[8, 999]]]}}, "5": {"brute_force": {"itens": [[6, 974], [4, 101], [5, 618], [4, 284], [5, 1005], [3, 205], [9, 867], [2, 690], [6, 686], [6, 631]], "total_time": "44.945248", "waste": 10, "solution": [[[6, 631], [2, 690]], [[6, 686], [3, 205]], [[9, 867]], [[5, 1005], [4, 284]], [[5, 618], [4, 101]], [[6, 974]]]}, "greedy": {"itens": [[6, 974], [4, 101], [5, 618], [4, 284], [5, 1005], [3, 205], [9, 867], [2, 690], [6, 686], [6, 631]], "total_time": "0.000029", "waste": 20, "solution": [[[4, 101], [3, 205], [2, 690]], [[4, 284], [5, 618]], [[6, 631]], [[6, 686]], [[9, 867]], [[6, 974]], [[5, 1005]]]}}, "6": {"brute_force": {"itens": [[6, 486], [1, 435], [2, 997], [9, 874], [7, 901], [8, 170], [1, 173], [3, 216], [8, 471], [9, 709]], "total_time": "41.998889", "waste": 6, "solution": [[[9, 709], [1, 173]], [[8, 471], [2, 997]], [[3, 216], [7, 901]], [[8, 170], [1, 435]], [[9, 874]], [[6, 486]]]}, "greedy": {"itens": [[6, 486], [1, 435], [2, 997], [9, 874], [7, 901], [8, 170], [1, 173], [3, 216], [8, 471], [9, 709]], "total_time": "0.000028", "waste": 6, "solution": [[[8, 170], [1, 173], [1, 435]], [[3, 216], [6, 486]], [[8, 471], [2, 997]], [[9, 709]], [[9, 874]], [[7, 901]]]}}, "7": {"brute_force": {"itens": [[6, 333], [7, 377], [9, 677], [3, 38], [7, 1005], [5, 600], [8, 552], [2, 439], [3, 98], [4, 803]], "total_time": "44.952820", "waste": 16, "solution": [[[4, 803], [3, 98], [2, 439]], [[8, 552]], [[5, 600], [3, 38]], [[7, 1005]], [[9, 677]], [[7, 377]], [[6, 333]]]}, "greedy": {"itens": [[6, 333], [7, 377], [9, 677], [3, 38], [7, 1005], [5, 600], [8, 552], [2, 439], [3, 98], [4, 803]], "total_time": "0.000032", "waste": 16, "solution": [[[3, 38], [3, 98], [2, 439]], [[6, 333], [4, 803]], [[7, 377]], [[8, 552]], [[5, 600]], [[9, 677]], [[7, 1005]]]}}, "8": {"brute_force": {"itens": [[3, 307], [4, 331], [8, 455], [6, 408], [5, 94], [5, 473], [8, 456], [5, 214], [5, 521], [6, 506]], "total_time": "46.515929", "waste": 5, "solution": [[[6, 506], [4, 331]], [[5, 521], [5, 214]], [[8, 456]], [[5, 473], [5, 94]], [[6, 408], [3, 307]], [[8, 455]]]}, "greedy": {"itens": [[3, 307], [4, 331], [8, 455], [6, 408], [5, 94], [5, 473], [8, 456], [5, 214], [5, 521], [6, 506]], "total_time": "0.000030", "waste": 15, "solution": [[[5, 94], [5, 214]], [[3, 307], [4, 331]], [[6, 408]], [[8, 455]], [[8, 456]], [[5, 473], [5, 521]], [[6, 506]]]}}, "9": {"brute_force": {"itens": [[8, 741], [9, 307], [7, 656], [5, 758], [2, 378], [4, 725], [9, 842], [9, 53], [7, 722], [7, 440]], "total_time": "53.664598", "waste": 13, "solution": [[[7, 440], [2, 378]], [[7, 722]], [[9, 53]], [[9, 842]], [[4, 725], [5, 758]], [[7, 656]], [[9, 307]], [[8, 741]]]}, "greedy": {"itens": [[8, 741], [9, 307], [7, 656], [5, 758], [2, 378], [4, 725], [9, 842], [9, 53], [7, 722], [7, 440]], "total_time": "0.000031", "waste": 13, "solution": [[[9, 53]], [[9, 307]], [[2, 378], [7, 440]], [[7, 656]], [[7, 722]], [[4, 725], [5, 758]], [[8, 741]], [[9, 842]]]}}, "10": {"brute_force": {"itens": [[5, 784], [8, 118], [5, 585], [8, 604], [1, 755], [5, 884], [2, 349], [4, 273], [6, 18], [5, 959]], "total_time": "41.451370", "waste": 11, "solution": [[[5, 959], [4, 273], [1, 755]], [[6, 18], [2, 349]], [[5, 884], [5, 585]], [[8, 604]], [[8, 118]], [[5, 784]]]}, "greedy": {"itens": [[5, 784], [8, 118], [5, 585], [8, 604], [1, 755], [5, 884], [2, 349], [4, 273], [6, 18], [5, 959]], "total_time": "0.000028", "waste": 11, "solution": [[[6, 18], [4, 273]], [[8, 118], [2, 349]], [[5, 585], [1, 755]], [[8, 604]], [[5, 784], [5, 884]], [[5, 959]]]}}, "11": {"brute_force": {"itens": [[8, 712], [5, 698], [1, 136], [3, 774], [1, 784], [2, 902], [1, 516], [6, 658], [5, 374], [8, 110]], "total_time": "36.034491", "waste": 10, "solution": [[[8, 110], [1, 516], [1, 784]], [[5, 374], [2, 902], [3, 774]], [[6, 658], [1, 136]], [[5, 698]], [[8, 712]]]}, "greedy": {"itens": [[8, 712], [5, 698], [1, 136], [3, 774], [1, 784], [2, 902], [1, 516], [6, 658], [5, 374], [8, 110]], "total_time": "0.000026", "waste": 0, "solution": [[[8, 110], [1, 136], [1, 516]], [[5, 374], [5, 698]], [[6, 658], [3, 774], [1, 784]], [[8, 712], [2, 902]]]}}, "12": {"brute_force": {"itens": [[3, 815], [3, 636], [7, 989], [3, 820], [8, 89], [1, 33], [5, 891], [5, 514], [7, 418], [6, 810]], "total_time": "41.632389", "waste": 2, "solution": [[[6, 810], [1, 33], [3, 820]], [[7, 418], [3, 636]], [[5, 514], [5, 891]], [[8, 89]], [[7, 989], [3, 815]]]}, "greedy": {"itens": [[3, 815], [3, 636], [7, 989], [3, 820], [8, 89], [1, 33], [5, 891], [5, 514], [7, 418], [6, 810]], "total_time": "0.000029", "waste": 12, "solution": [[[1, 33], [8, 89]], [[7, 418], [3, 636]], [[5, 514], [3, 815]], [[6, 810], [3, 820]], [[5, 891]], [[7, 989]]]}}, "13": {"brute_force": {"itens": [[2, 455], [7, 842], [1, 559], [7, 163], [3, 339], [7, 727], [8, 697], [8, 387], [2, 636], [5, 419]], "total_time": "41.251264", "waste": 10, "solution": [[[5, 419], [2, 636], [3, 339]], [[8, 387], [1, 559]], [[8, 697], [2, 455]], [[7, 727]], [[7, 163]], [[7, 842]]]}, "greedy": {"itens": [[2, 455], [7, 842], [1, 559], [7, 163], [3, 339], [7, 727], [8, 697], [8, 387], [2, 636], [5, 419]], "total_time": "0.000028", "waste": 10, "solution": [[[7, 163], [3, 339]], [[8, 387], [2, 455]], [[5, 419], [1, 559], [2, 636]], [[8, 697]], [[7, 727]], [[7, 842]]]}}, "14": {"brute_force": {"itens": [[3, 783], [2, 532], [1, 762], [8, 673], [1, 902], [4, 617], [8, 383], [4, 935], [5, 265], [7, 580]], "total_time": "37.550386", "waste": 7, "solution": [[[7, 580], [1, 902], [1, 762]], [[5, 265], [4, 935]], [[8, 383], [2, 532]], [[4, 617], [3, 783]], [[8, 673]]]}, "greedy": {"itens": [[3, 783], [2, 532], [1, 762], [8, 673], [1, 902], [4, 617], [8, 383], [4, 935], [5, 265], [7, 580]], "total_time": "0.000049", "waste": 7, "solution": [[[5, 265], [2, 532], [1, 762], [1, 902]], [[8, 383]], [[7, 580], [3, 783]], [[4, 617], [4, 935]], [[8, 673]]]}}, "15": {"brute_force": {"itens": [[9, 49], [9, 227], [5, 742], [5, 783], [3, 410], [1, 186], [2, 621], [1, 231], [6, 954], [1, 989]], "total_time": "36.342820", "waste": 8, "solution": [[[1, 989], [6, 954], [1, 231], [2, 621]], [[1, 186], [3, 410], [5, 783]], [[5, 742]], [[9, 227]], [[9, 49]]]}, "greedy": {"itens": [[9, 49], [9, 227], [5, 742], [5, 783], [3, 410], [1, 186], [2, 621], [1, 231], [6, 954], [1, 989]], "total_time": "0.000027", "waste": 8, "solution": [[[9, 49], [1, 186]], [[9, 227], [1, 231]], [[3, 410], [2, 621], [5, 742]], [[5, 783], [1, 989]], [[6, 954]]]}}, "16": {"brute_force": {"itens": [[3, 175], [7, 469], [9, 126], [1, 714], [1, 185], [4, 944], [3, 767], [4, 277], [1, 752], [8, 470]], "total_time": "36.265444", "waste": 9, "solution": [[[8, 470], [1, 752], [1, 185]], [[4, 277], [3, 767], [1, 714]], [[4, 944], [3, 175]], [[9, 126]], [[7, 469]]]}, "greedy": {"itens": [[3, 175], [7, 469], [9, 126], [1, 714], [1, 185], [4, 944], [3, 767], [4, 277], [1, 752], [8, 470]], "total_time": "0.000026", "waste": 9, "solution": [[[9, 126], [1, 185]], [[3, 175], [4, 277], [1, 714], [1, 752]], [[7, 469], [3, 767]], [[8, 470]], [[4, 944]]]}}, "17": {"brute_force": {"itens": [[7, 409], [2, 474], [1, 784], [1, 139], [7, 73], [7, 190], [6, 65], [4, 362], [4, 920], [1, 158]], "total_time": "36.262368", "waste": 10, "solution": [[[1, 158], [4, 920], [4, 362], [1, 139]], [[6, 65], [1, 784], [2, 474]], [[7, 190]], [[7, 73]], [[7, 409]]]}, "greedy": {"itens": [[7, 409], [2, 474], [1, 784], [1, 139], [7, 73], [7, 190], [6, 65], [4, 362], [4, 920], [1, 158]], "total_time": "0.000026", "waste": 10, "solution": [[[6, 65], [1, 139], [1, 158], [2, 474]], [[7, 73], [1, 784]], [[7, 190]], [[4, 362], [4, 920]], [[7, 409]]]}}, "18": {"brute_force": {"itens": [[4, 496], [9, 971], [9, 506], [5, 648], [9, 816], [2, 201], [6, 844], [4, 37], [2, 634], [3, 189]], "total_time": "41.045274", "waste": 7, "solution": [[[3, 189], [2, 634], [4, 37]], [[6, 844], [2, 201]], [[9, 816]], [[5, 648], [4, 496]], [[9, 506]], [[9, 971]]]}, "greedy": {"itens": [[4, 496], [9, 971], [9, 506], [5, 648], [9, 816], [2, 201], [6, 844], [4, 37], [2, 634], [3, 189]], "total_time": "0.000027", "waste": 17, "solution": [[[4, 37], [3, 189], [2, 201]], [[4, 496], [2, 634]], [[9, 506]], [[5, 648]], [[9, 816]], [[6, 844]], [[9, 971]]]}}, "19": {"brute_force": {"itens": [[9, 714], [2, 806], [3, 582], [9, 520], [9, 509], [4, 79], [5, 614], [9, 333], [1, 955], [1, 278]], "total_time": "39.076684", "waste": 8, "solution": [[[1, 278], [1, 955], [5, 614], [3, 582]], [[9, 333]], [[4, 79], [2, 806]], [[9, 509]], [[9, 520]], [[9, 714]]]}, "greedy": {"itens": [[9, 714], [2, 806], [3, 582], [9, 520], [9, 509], [4, 79], [5, 614], [9, 333], [1, 955], [1, 278]], "total_time": "0.000026", "waste": 8, "solution": [[[4, 79], [1, 278], [3, 582], [2, 806]], [[9, 333], [1, 955]], [[9, 509]], [[9, 520]], [[5, 614]], [[9, 714]]]}}, "20": {"brute_force": {"itens": [[9, 514], [3, 975], [9, 643], [4, 325], [4, 983], [6, 191], [4, 618], [4, 223], [2, 634], [7, 576]], "total_time": "40.878899", "waste": 8, "solution": [[[7, 576], [2, 634]], [[4, 223], [4, 618]], [[6, 191], [4, 983]], [[4, 325], [3, 975]], [[9, 643]], [[9, 514]]]}, "greedy": {"itens": [[9, 514], [3, 975], [9, 643], [4, 325], [4, 983], [6, 191], [4, 618], [4, 223], [2, 634], [7, 576]], "total_time": "0.000025", "waste": 8, "solution": [[[6, 191], [4, 223]], [[4, 325], [4, 618], [2, 634]], [[9, 514]], [[7, 576], [3, 975]], [[9, 643]], [[4, 983]]]}}, "21": {"brute_force": {"itens": [[6, 101], [9, 724], [8, 326], [8, 179], [7, 103], [9, 587], [7, 557], [7, 904], [7, 695], [6, 574]], "total_time": "61.499645", "waste": 26, "solution": [[[6, 574]], [[7, 695]], [[7, 904]], [[7, 557]], [[9, 587]], [[7, 103]], [[8, 179]], [[8, 326]], [[9, 724]], [[6, 101]]]}, "greedy": {"itens": [[6, 101], [9, 724], [8, 326], [8, 179], [7, 103], [9, 587], [7, 557], [7, 904], [7, 695], [6, 574]], "total_time": "0.000031", "waste": 26, "solution": [[[6, 101]], [[7, 103]], [[8, 179]], [[8, 326]], [[7, 557]], [[6, 574]], [[9, 587]], [[7, 695]], [[9, 724]], [[7, 904]]]}}, "22": {"brute_force": {"itens": [[2, 268], [6, 100], [4, 99], [4, 765], [2, 370], [7, 227], [2, 77], [2, 76], [2, 991], [3, 763]], "total_time": "32.129426", "waste": 6, "solution": [[[3, 763], [2, 991], [2, 76], [2, 77]], [[7, 227], [2, 370]], [[4, 765], [4, 99], [2, 268]], [[6, 100]]]}, "greedy": {"itens": [[2, 268], [6, 100], [4, 99], [4, 765], [2, 370], [7, 227], [2, 77], [2, 76], [2, 991], [3, 763]], "total_time": "0.000024", "waste": 6, "solution": [[[2, 76], [2, 77], [4, 99], [2, 268]], [[6, 100], [2, 370], [2, 991]], [[7, 227], [3, 763]], [[4, 765]]]}}, "23": {"brute_force": {"itens": [[6, 306], [4, 621], [6, 341], [5, 116], [3, 896], [2, 819], [6, 589], [3, 532], [5, 73], [2, 698]], "total_time": "36.270412", "waste": 8, "solution": [[[2, 698], [5, 73], [3, 532]], [[6, 589], [2, 819]], [[3, 896], [5, 116]], [[6, 341], [4, 621]], [[6, 306]]]}, "greedy": {"itens": [[6, 306], [4, 621], [6, 341], [5, 116], [3, 896], [2, 819], [6, 589], [3, 532], [5, 73], [2, 698]], "total_time": "0.000026", "waste": 8, "solution": [[[5, 73], [5, 116]], [[6, 306], [3, 532]], [[6, 341], [4, 621]], [[6, 589], [2, 698], [2, 819]], [[3, 896]]]}}, "24": {"brute_force": {"itens": [[9, 980], [4, 457], [6, 743], [6, 532], [7, 332], [4, 16], [2, 51], [6, 832], [9, 255], [5, 731]], "total_time": "45.463775", "waste": 12, "solution": [[[5, 731], [2, 51]], [[9, 255]], [[6, 832], [4, 16]], [[7, 332]], [[6, 532], [4, 457]], [[6, 743]], [[9, 980]]]}, "greedy": {"itens": [[9, 980], [4, 457], [6, 743], [6, 532], [7, 332], [4, 16], [2, 51], [6, 832], [9, 255], [5, 731]], "total_time": "0.000029", "waste": 22, "solution": [[[4, 16], [2, 51], [4, 457]], [[9, 255]], [[7, 332]], [[6, 532]], [[5, 731]], [[6, 743]], [[6, 832]], [[9, 980]]]}}, "25": {"brute_force": {"itens": [[9, 257], [2, 27], [4, 560], [9, 318], [4, 786], [9, 143], [5, 416], [6, 990], [1, 950], [5, 649]], "total_time": "41.206355", "waste": 6, "solution": [[[5, 649], [1, 950], [4, 786]], [[6, 990], [4, 560]], [[5, 416], [2, 27]], [[9, 143]], [[9, 318]], [[9, 257]]]}, "greedy": {"itens": [[9, 257], [2, 27], [4, 560], [9, 318], [4, 786], [9, 143], [5, 416], [6, 990], [1, 950], [5, 649]], "total_time": "0.000026", "waste": 6, "solution": [[[2, 27], [5, 416], [1, 950]], [[9, 143]], [[9, 257]], [[9, 318]], [[4, 560], [5, 649]], [[4, 786], [6, 990]]]}}, "26": {"brute_force": {"itens": [[4, 858], [7, 584], [6, 168], [6, 274], [3, 56], [3, 645], [7, 753], [3, 396], [8, 806], [8, 624]], "total_time": "43.046367", "waste": 15, "solution": [[[8, 624]], [[8, 806]], [[3, 396], [7, 753]], [[3, 645], [3, 56], [4, 858]], [[6, 274]], [[6, 168]], [[7, 584]]]}, "greedy": {"itens": [[4, 858], [7, 584], [6, 168], [6, 274], [3, 56], [3, 645], [7, 753], [3, 396], [8, 806], [8, 624]], "total_time": "0.000026", "waste": 15, "solution": [[[3, 56], [6, 168]], [[6, 274], [3, 396]], [[7, 584], [3, 645]], [[8, 624]], [[7, 753]], [[8, 806]], [[4, 858]]]}}, "27": {"brute_force": {"itens": [[3, 612], [3, 562], [8, 934], [5, 821], [6, 529], [9, 487], [6, 875], [1, 599], [8, 27], [3, 873]], "total_time": "41.543805", "waste": 8, "solution": [[[3, 873], [1, 599], [6, 875]], [[8, 27]], [[9, 487]], [[6, 529], [3, 562]], [[5, 821], [3, 612]], [[8, 934]]]}, "greedy": {"itens": [[3, 612], [3, 562], [8, 934], [5, 821], [6, 529], [9, 487], [6, 875], [1, 599], [8, 27], [3, 873]], "total_time": "0.000030", "waste": 8, "solution": [[[8, 27], [1, 599]], [[9, 487]], [[6, 529], [3, 562]], [[3, 612], [5, 821]], [[3, 873], [6, 875]], [[8, 934]]]}}, "28": {"brute_force": {"itens": [[1, 956], [5, 863], [1, 756], [2, 870], [7, 920], [6, 768], [2, 139], [3, 880], [5, 704], [1, 718]], "total_time": "30.144970", "waste": 7, "solution": [[[1, 718], [5, 704], [3, 880], [1, 756]], [[2, 139], [6, 768], [2, 870]], [[7, 920], [1, 956]], [[5, 863]]]}, "greedy": {"itens": [[1, 956], [5, 863], [1, 756], [2, 870], [7, 920], [6, 768], [2, 139], [3, 880], [5, 704], [1, 718]], "total_time": "0.000022", "waste": 7, "solution": [[[2, 139], [5, 704], [1, 718], [1, 756], [1, 956]], [[6, 768], [2, 870]], [[5, 863], [3, 880]], [[7, 920]]]}}, "29": {"brute_force": {"itens": [[5, 56], [3, 89], [2, 1006], [8, 206], [5, 609], [5, 973], [2, 38], [4, 751], [1, 232], [5, 656]], "total_time": "34.790281", "waste": 10, "solution": [[[5, 656], [1, 232], [4, 751]], [[2, 38], [5, 973], [2, 1006]], [[5, 609], [3, 89]], [[8, 206]], [[5, 56]]]}, "greedy": {"itens": [[5, 56], [3, 89], [2, 1006], [8, 206], [5, 609], [5, 973], [2, 38], [4, 751], [1, 232], [5, 656]], "total_time": "0.000025", "waste": 10, "solution": [[[2, 38], [5, 56], [3, 89]], [[8, 206], [1, 232]], [[5, 609], [5, 656]], [[4, 751], [5, 973]], [[2, 1006]]]}}}